GetPhenoDecoder/GetPheno.py
GetPhenoDecoder/__init__.py
GetPhenoDecoder-1.0.dist-info/METADATA
GetPhenoDecoder-1.0.dist-info/WHEEL
GetPhenoDecoder-1.0.dist-info/top_level.txt
GetPhenoDecoder-1.0.dist-info/RECORD
