Metadata-Version: 2.1
Name: GetPhenoDecoder
Version: 1.0
Summary: A package for landscape-scale phenology extraction using vegetation index time series!
Home-page: UNKNOWN
Author: Rubisco Ren
Author-email: rubisco51999@gmail.com
License: UNKNOWN
Platform: UNKNOWN
Requires-Dist: numpy
Requires-Dist: scipy
Requires-Dist: matplotlib
